{
  "id": "5664643b-9c9e-4816-996a-7a75d0402c54",
  "prevId": "00000000-0000-0000-0000-000000000000",
  "version": "7",
  "dialect": "postgresql",
  "tables": {
    "public.poll": {
      "name": "poll",
      "schema": "",
      "columns": {
        "id": {
          "name": "id",
          "type": "uuid",
          "primaryKey": true,
          "notNull": true,
          "default": "gen_random_uuid()"
        },
        "user_id": {
          "name": "user_id",
          "type": "uuid",
          "primaryKey": false,
          "notNull": true
        },
        "heading": {
          "name": "heading",
          "type": "text",
          "primaryKey": false,
          "notNull": false
        },
        "img": {
          "name": "img",
          "type": "text",
          "primaryKey": false,
          "notNull": false
        },
        "options": {
          "name": "options",
          "type": "text[]",
          "primaryKey": false,
          "notNull": true,
          "default": "ARRAY[]::text[]"
        }
      },
      "indexes": {},
      "foreignKeys": {
        "poll_user_id_user_id_fk": {
          "name": "poll_user_id_user_id_fk",
          "tableFrom": "poll",
          "tableTo": "user",
          "columnsFrom": [
            "user_id"
          ],
          "columnsTo": [
            "id"
          ],
          "onDelete": "no action",
          "onUpdate": "no action"
        }
      },
      "compositePrimaryKeys": {},
      "uniqueConstraints": {}
    },
    "public.session": {
      "name": "session",
      "schema": "",
      "columns": {
        "id": {
          "name": "id",
          "type": "text",
          "primaryKey": true,
          "notNull": true
        },
        "user_id": {
          "name": "user_id",
          "type": "uuid",
          "primaryKey": false,
          "notNull": true
        },
        "expires_at": {
          "name": "expires_at",
          "type": "timestamp with time zone",
          "primaryKey": false,
          "notNull": true
        }
      },
      "indexes": {},
      "foreignKeys": {
        "session_user_id_user_id_fk": {
          "name": "session_user_id_user_id_fk",
          "tableFrom": "session",
          "tableTo": "user",
          "columnsFrom": [
            "user_id"
          ],
          "columnsTo": [
            "id"
          ],
          "onDelete": "no action",
          "onUpdate": "no action"
        }
      },
      "compositePrimaryKeys": {},
      "uniqueConstraints": {}
    },
    "public.user": {
      "name": "user",
      "schema": "",
      "columns": {
        "id": {
          "name": "id",
          "type": "uuid",
          "primaryKey": true,
          "notNull": true,
          "default": "gen_random_uuid()"
        },
        "username": {
          "name": "username",
          "type": "text",
          "primaryKey": false,
          "notNull": true
        },
        "password_hash": {
          "name": "password_hash",
          "type": "text",
          "primaryKey": false,
          "notNull": true
        }
      },
      "indexes": {},
      "foreignKeys": {},
      "compositePrimaryKeys": {},
      "uniqueConstraints": {
        "user_username_unique": {
          "name": "user_username_unique",
          "nullsNotDistinct": false,
          "columns": [
            "username"
          ]
        }
      }
    },
    "public.vote": {
      "name": "vote",
      "schema": "",
      "columns": {
        "poll_id": {
          "name": "poll_id",
          "type": "uuid",
          "primaryKey": false,
          "notNull": true
        },
        "identifier_type": {
          "name": "identifier_type",
          "type": "identifier",
          "typeSchema": "public",
          "primaryKey": false,
          "notNull": false
        },
        "identifier": {
          "name": "identifier",
          "type": "text",
          "primaryKey": false,
          "notNull": false
        },
        "label": {
          "name": "label",
          "type": "text",
          "primaryKey": false,
          "notNull": true
        }
      },
      "indexes": {},
      "foreignKeys": {
        "vote_poll_id_poll_id_fk": {
          "name": "vote_poll_id_poll_id_fk",
          "tableFrom": "vote",
          "tableTo": "poll",
          "columnsFrom": [
            "poll_id"
          ],
          "columnsTo": [
            "id"
          ],
          "onDelete": "cascade",
          "onUpdate": "no action"
        }
      },
      "compositePrimaryKeys": {},
      "uniqueConstraints": {}
    }
  },
  "enums": {
    "public.identifier": {
      "name": "identifier",
      "schema": "public",
      "values": [
        "ip",
        "user"
      ]
    }
  },
  "schemas": {},
  "_meta": {
    "columns": {},
    "schemas": {},
    "tables": {}
  }
}